qstats/__init__.py
qstats/qstats.py
qstats/utils.py
qstats-0.3.1.data/scripts/QSTAT
qstats-0.3.1.data/scripts/qstat_bokeh.py
qstats-0.3.1.dist-info/LICENSE
qstats-0.3.1.dist-info/METADATA
qstats-0.3.1.dist-info/WHEEL
qstats-0.3.1.dist-info/top_level.txt
qstats-0.3.1.dist-info/RECORD
