Metadata-Version: 2.1
Name: qstats
Version: 0.3.1
Summary: SGE qstat info
Home-page: https://github.com/shane-breeze/qstats
Author: Shane Breeze
Author-email: sdb15@ic.ac.uk
License: UNKNOWN
Platform: UNKNOWN
Classifier: Development Status :: 4 - Beta
Classifier: Programming Language :: Python :: 3
Classifier: License :: OSI Approved :: MIT License
Classifier: Operating System :: OS Independent
Requires-Python: >=3.8
Requires-Dist: numpy (>=1.18.1)
Requires-Dist: pandas (>=0.25.3)
Requires-Dist: xmltodict (>=0.12.0)
Requires-Dist: tabulate (>=0.8.7)
Requires-Dist: pyyaml (>=3.10)
Requires-Dist: bokeh (>=2.1.1)
